ads1256/__init__.py
ads1256/ads1256.py
ads1256/constants.py
ads1256-0.2.0.dist-info/LICENSE
ads1256-0.2.0.dist-info/METADATA
ads1256-0.2.0.dist-info/WHEEL
ads1256-0.2.0.dist-info/RECORD
